ruia_cache/__init__.py
ruia_cache/request.py
ruia_cache/response.py
ruia_cache/serializers.py
ruia_cache/spider.py
ruia_cache/utils.py
ruia_cache/cache_patch/__init__.py
ruia_cache/cache_patch/req_cache.py
ruia_cache/cache_patch/resp_cache.py
ruia_cache-0.0.2.dist-info/LICENSE
ruia_cache-0.0.2.dist-info/METADATA
ruia_cache-0.0.2.dist-info/WHEEL
ruia_cache-0.0.2.dist-info/top_level.txt
ruia_cache-0.0.2.dist-info/RECORD
